opioidrl/__init__.py
opioidrl/example_2.py
opioidrl/meth.py
opioidrl/train.py
opioidrl-0.0.2.dist-info/LICENSE
opioidrl-0.0.2.dist-info/METADATA
opioidrl-0.0.2.dist-info/WHEEL
opioidrl-0.0.2.dist-info/RECORD
