Metadata-Version: 2.1
Name: opioidrl
Version: 0.0.2
Summary: Paper - Pytorch
Home-page: https://github.com/kyegomez/OpioidRL
License: MIT
Keywords: artificial intelligence,deep learning,optimizers,Prompt Engineering
Author: Kye Gomez
Author-email: kye@apac.ai
Requires-Python: >=3.10,<4.0
Classifier: Development Status :: 4 - Beta
Classifier: Intended Audience :: Developers
Classifier: License :: OSI Approved :: MIT License
Classifier: Programming Language :: Python :: 3
Classifier: Programming Language :: Python :: 3.10
Classifier: Programming Language :: Python :: 3.11
Classifier: Programming Language :: Python :: 3.12
Classifier: Programming Language :: Python :: 3.9
Classifier: Topic :: Scientific/Engineering :: Artificial Intelligence
Requires-Dist: gymnasium
Requires-Dist: loguru
Requires-Dist: numpy
Requires-Dist: random2
Requires-Dist: stable-baselines3
Requires-Dist: torch
Requires-Dist: transformers
Project-URL: Documentation, https://github.com/kyegomez/OpioidRL
Project-URL: Repository, https://github.com/kyegomez/OpioidRL
